fc_dc_bigdata.py
fc_qwh-1.0.dist-info/METADATA
fc_qwh-1.0.dist-info/WHEEL
fc_qwh-1.0.dist-info/top_level.txt
fc_qwh-1.0.dist-info/RECORD
